minesweeper/__init__.py
minesweeper/error.py
minesweeper/generator.py
minesweeper/preset.py
minesweeperPy-2.1.dist-info/LICENSE
minesweeperPy-2.1.dist-info/METADATA
minesweeperPy-2.1.dist-info/WHEEL
minesweeperPy-2.1.dist-info/top_level.txt
minesweeperPy-2.1.dist-info/RECORD
