Metadata-Version: 2.1
Name: minesweeperPy
Version: 2.1
Summary: A simple minesweeper generator for Python 3
Home-page: https://github.com/stshrewsburyDev/minesweeperPy
Author: stshrewsburyDev
Author-email: 
License: MIT
Project-URL: Source, https://github.com/stshrewsburyDev/minesweeperPy
Project-URL: Documentation, https://minesweeperPy.readthedocs.io/en/latest/
Platform: UNKNOWN
Classifier: Programming Language :: Python
Classifier: Programming Language :: Python :: 3
Classifier: License :: OSI Approved :: MIT License
Classifier: Operating System :: OS Independent
Classifier: Topic :: Utilities
Classifier: Intended Audience :: Developers
Requires-Python: >=3.5
License-File: LICENSE
